gyat_model/__init__.py
gyatmodel1-0.1.2.dist-info/licenses/LICENSE
gyatmodel1-0.1.2.dist-info/METADATA
gyatmodel1-0.1.2.dist-info/WHEEL
gyatmodel1-0.1.2.dist-info/top_level.txt
gyatmodel1-0.1.2.dist-info/RECORD
