Metadata-Version: 2.4
Name: gyatModel1
Version: 0.1.2
Summary: A sample package that prints text file content
Author: Micheal Scofield
Classifier: Programming Language :: Python :: 3
License-File: LICENSE
Dynamic: author
Dynamic: classifier
Dynamic: description
Dynamic: description-content-type
Dynamic: license-file
Dynamic: summary
